{"0": {"title": "skalunda-giant", "s_id": 107, "id": 0, "words": [{"id": 0, "word": "In", "marked": 0, "stop": 1}, {"id": 1, "word": "the", "marked": 0, "stop": 1}, {"id": 2, "word": "Skalunda", "marked": 0, "stop": 1}, {"id": 3, "word": "mountain", "marked": 0, "stop": 0}, {"id": 4, "word": ",", "marked": 0, "stop": 1}, {"id": 5, "word": "near", "marked": 0, "stop": 1}, {"id": 6, "word": "the", "marked": 0, "stop": 1}, {"id": 7, "word": "church", "marked": 0, "stop": 0}, {"id": 8, "word": ",", "marked": 0, "stop": 1}, {"id": 9, "word": "there", "marked": 0, "stop": 1}, {"id": 10, "word": "once", "marked": 0, "stop": 1}, {"id": 11, "word": "lived", "marked": 0, "stop": 0}, {"id": 12, "word": "a", "marked": 0, "stop": 1}, {"id": 13, "word": "giant", "marked": 0, "stop": 0}, {"id": 14, "word": "in", "marked": 0, "stop": 1}, {"id": 15, "word": "the", "marked": 0, "stop": 1}, {"id": 16, "word": "early", "marked": 0, "stop": 0}, {"id": 17, "word": "days", "marked": 0, "stop": 0}, {"id": 18, "word": ",", "marked": 0, "stop": 1}, {"id": 19, "word": "who", "marked": 0, "stop": 1}, {"id": 20, "word": "no", "marked": 0, "stop": 1}, {"id": 21, "word": "longer", "marked": 0, "stop": 0}, {"id": 22, "word": "felt", "marked": 0, "stop": 0}, {"id": 23, "word": "comfortable", "marked": 0, "stop": 0}, {"id": 24, "word": "after", "marked": 0, "stop": 1}, {"id": 25, "word": "the", "marked": 0, "stop": 1}, {"id": 26, "word": "church", "marked": 0, "stop": 0}, {"id": 27, "word": "had", "marked": 0, "stop": 1}, {"id": 28, "word": "been", "marked": 0, "stop": 1}, {"id": 29, "word": "built", "marked": 0, "stop": 0}, {"id": 30, "word": "there", "marked": 0, "stop": 1}, {"id": 31, "word": ".", "marked": 0, "stop": 1}, {"id": 32, "word": "He", "marked": 0, "stop": 1}, {"id": 33, "word": "decided", "marked": 0, "stop": 0}, {"id": 34, "word": "that", "marked": 0, "stop": 1}, {"id": 35, "word": "he", "marked": 0, "stop": 1}, {"id": 36, "word": "could", "marked": 0, "stop": 1}, {"id": 37, "word": "no", "marked": 0, "stop": 1}, {"id": 38, "word": "longer", "marked": 0, "stop": 0}, {"id": 39, "word": "stand", "marked": 0, "stop": 0}, {"id": 40, "word": "the", "marked": 0, "stop": 1}, {"id": 41, "word": "ringing", "marked": 0, "stop": 0}, {"id": 42, "word": "of", "marked": 0, "stop": 1}, {"id": 43, "word": "the", "marked": 0, "stop": 1}, {"id": 44, "word": "church", "marked": 0, "stop": 0}, {"id": 45, "word": "bells", "marked": 0, "stop": 0}, {"id": 46, "word": ";", "marked": 0, "stop": 1}, {"id": 47, "word": "so", "marked": 0, "stop": 1}, {"id": 48, "word": "he", "marked": 0, "stop": 1}, {"id": 49, "word": "emigrated", "marked": 0, "stop": 0}, {"id": 50, "word": "and", "marked": 0, "stop": 1}, {"id": 51, "word": "settled", "marked": 0, "stop": 0}, {"id": 52, "word": "down", "marked": 0, "stop": 1}, {"id": 53, "word": "on", "marked": 0, "stop": 1}, {"id": 54, "word": "an", "marked": 0, "stop": 1}, {"id": 55, "word": "island", "marked": 0, "stop": 0}, {"id": 56, "word": "far", "marked": 0, "stop": 0}, {"id": 57, "word": "out", "marked": 0, "stop": 1}, {"id": 58, "word": "in", "marked": 0, "stop": 1}, {"id": 59, "word": "the", "marked": 0, "stop": 1}, {"id": 60, "word": "North", "marked": 0, "stop": 0}, {"id": 61, "word": "Sea", "marked": 0, "stop": 0}, {"id": 62, "word": ".", "marked": 0, "stop": 1}, {"id": 63, "word": "Once", "marked": 0, "stop": 1}, {"id": 64, "word": "upon", "marked": 0, "stop": 1}, {"id": 65, "word": "a", "marked": 0, "stop": 1}, {"id": 66, "word": "time", "marked": 0, "stop": 1}, {"id": 67, "word": "a", "marked": 0, "stop": 1}, {"id": 68, "word": "ship", "marked": 0, "stop": 0}, {"id": 69, "word": "was", "marked": 0, "stop": 1}, {"id": 70, "word": "wrecked", "marked": 0, "stop": 0}, {"id": 71, "word": "on", "marked": 0, "stop": 1}, {"id": 72, "word": "this", "marked": 0, "stop": 1}, {"id": 73, "word": "island", "marked": 0, "stop": 0}, {"id": 74, "word": ",", "marked": 0, "stop": 1}, {"id": 75, "word": "and", "marked": 0, "stop": 1}, {"id": 76, "word": "among", "marked": 0, "stop": 1}, {"id": 77, "word": "those", "marked": 0, "stop": 1}, {"id": 78, "word": "saved", "marked": 0, "stop": 0}, {"id": 79, "word": "were", "marked": 0, "stop": 1}, {"id": 80, "word": "several", "marked": 0, "stop": 1}, {"id": 81, "word": "people", "marked": 0, "stop": 0}, {"id": 82, "word": "from", "marked": 0, "stop": 1}, {"id": 83, "word": "Skalunda", "marked": 0, "stop": 1}, {"id": 84, "word": ".", "marked": 0, "stop": 1}]}, "1": {"title": "skalunda-giant", "s_id": 107, "id": 1, "words": [{"id": 0, "word": "``", "marked": 0, "stop": 1}, {"id": 1, "word": "From", "marked": 0, "stop": 1}, {"id": 2, "word": "where", "marked": 0, "stop": 1}, {"id": 3, "word": "do", "marked": 0, "stop": 1}, {"id": 4, "word": "you", "marked": 0, "stop": 1}, {"id": 5, "word": "hail", "marked": 0, "stop": 0}, {"id": 6, "word": "?", "marked": 0, "stop": 1}, {"id": 7, "word": "''", "marked": 0, "stop": 1}, {"id": 8, "word": "asked", "marked": 0, "stop": 0}, {"id": 9, "word": "the", "marked": 0, "stop": 1}, {"id": 10, "word": "giant", "marked": 0, "stop": 0}, {"id": 11, "word": ",", "marked": 0, "stop": 1}, {"id": 12, "word": "who", "marked": 0, "stop": 1}, {"id": 13, "word": "by", "marked": 0, "stop": 1}, {"id": 14, "word": "now", "marked": 0, "stop": 1}, {"id": 15, "word": "had", "marked": 0, "stop": 1}, {"id": 16, "word": "grown", "marked": 0, "stop": 0}, {"id": 17, "word": "old", "marked": 0, "stop": 1}, {"id": 18, "word": "and", "marked": 0, "stop": 1}, {"id": 19, "word": "blind", "marked": 0, "stop": 0}, {"id": 20, "word": ",", "marked": 0, "stop": 1}, {"id": 21, "word": "and", "marked": 0, "stop": 1}, {"id": 22, "word": "sat", "marked": 0, "stop": 1}, {"id": 23, "word": "warming", "marked": 0, "stop": 0}, {"id": 24, "word": "himself", "marked": 0, "stop": 1}, {"id": 25, "word": "before", "marked": 0, "stop": 1}, {"id": 26, "word": "a", "marked": 0, "stop": 1}, {"id": 27, "word": "log", "marked": 0, "stop": 0}, {"id": 28, "word": "fire", "marked": 0, "stop": 0}, {"id": 29, "word": ".", "marked": 0, "stop": 1}, {"id": 30, "word": "``", "marked": 0, "stop": 1}, {"id": 31, "word": "We", "marked": 0, "stop": 1}, {"id": 32, "word": "are", "marked": 0, "stop": 1}, {"id": 33, "word": "from", "marked": 0, "stop": 1}, {"id": 34, "word": "Skalunda", "marked": 0, "stop": 1}, {"id": 35, "word": ",", "marked": 0, "stop": 1}, {"id": 36, "word": "''", "marked": 0, "stop": 1}, {"id": 37, "word": "said", "marked": 0, "stop": 1}, {"id": 38, "word": "one", "marked": 0, "stop": 1}, {"id": 39, "word": "of", "marked": 0, "stop": 1}, {"id": 40, "word": "the", "marked": 0, "stop": 1}, {"id": 41, "word": "men", "marked": 0, "stop": 0}, {"id": 42, "word": "saved", "marked": 0, "stop": 0}, {"id": 43, "word": ".", "marked": 0, "stop": 1}, {"id": 44, "word": "``", "marked": 0, "stop": 1}, {"id": 45, "word": "Give", "marked": 0, "stop": 1}, {"id": 46, "word": "me", "marked": 0, "stop": 1}, {"id": 47, "word": "your", "marked": 0, "stop": 1}, {"id": 48, "word": "hand", "marked": 0, "stop": 0}, {"id": 49, "word": ",", "marked": 0, "stop": 1}, {"id": 50, "word": "so", "marked": 0, "stop": 1}, {"id": 51, "word": "that", "marked": 0, "stop": 1}, {"id": 52, "word": "I", "marked": 0, "stop": 1}, {"id": 53, "word": "may", "marked": 0, "stop": 1}, {"id": 54, "word": "feel", "marked": 0, "stop": 0}, {"id": 55, "word": "whether", "marked": 0, "stop": 1}, {"id": 56, "word": "there", "marked": 0, "stop": 1}, {"id": 57, "word": "is", "marked": 0, "stop": 1}, {"id": 58, "word": "still", "marked": 0, "stop": 1}, {"id": 59, "word": "warm", "marked": 0, "stop": 0}, {"id": 60, "word": "blood", "marked": 0, "stop": 0}, {"id": 61, "word": "to", "marked": 0, "stop": 1}, {"id": 62, "word": "be", "marked": 0, "stop": 1}, {"id": 63, "word": "found", "marked": 0, "stop": 0}, {"id": 64, "word": "in", "marked": 0, "stop": 1}, {"id": 65, "word": "the", "marked": 0, "stop": 1}, {"id": 66, "word": "Swedish", "marked": 0, "stop": 0}, {"id": 67, "word": "land", "marked": 0, "stop": 0}, {"id": 68, "word": ",", "marked": 0, "stop": 1}, {"id": 69, "word": "''", "marked": 0, "stop": 1}, {"id": 70, "word": "said", "marked": 0, "stop": 1}, {"id": 71, "word": "the", "marked": 0, "stop": 1}, {"id": 72, "word": "giant", "marked": 0, "stop": 0}, {"id": 73, "word": ".", "marked": 0, "stop": 1}]}, "2": {"title": "skalunda-giant", "s_id": 107, "id": 2, "words": [{"id": 0, "word": "The", "marked": 0, "stop": 1}, {"id": 1, "word": "man", "marked": 0, "stop": 0}, {"id": 2, "word": ",", "marked": 0, "stop": 1}, {"id": 3, "word": "who", "marked": 0, "stop": 1}, {"id": 4, "word": "feared", "marked": 0, "stop": 0}, {"id": 5, "word": "to", "marked": 0, "stop": 1}, {"id": 6, "word": "shake", "marked": 0, "stop": 0}, {"id": 7, "word": "hands", "marked": 0, "stop": 1}, {"id": 8, "word": "with", "marked": 0, "stop": 1}, {"id": 9, "word": "the", "marked": 0, "stop": 1}, {"id": 10, "word": "giant", "marked": 0, "stop": 0}, {"id": 11, "word": ",", "marked": 0, "stop": 1}, {"id": 12, "word": "drew", "marked": 0, "stop": 1}, {"id": 13, "word": "a", "marked": 0, "stop": 1}, {"id": 14, "word": "red-hot", "marked": 0, "stop": 0}, {"id": 15, "word": "bar", "marked": 0, "stop": 0}, {"id": 16, "word": "of", "marked": 0, "stop": 1}, {"id": 17, "word": "iron", "marked": 0, "stop": 0}, {"id": 18, "word": "from", "marked": 0, "stop": 1}, {"id": 19, "word": "the", "marked": 0, "stop": 1}, {"id": 20, "word": "fire", "marked": 0, "stop": 0}, {"id": 21, "word": "and", "marked": 0, "stop": 1}, {"id": 22, "word": "handed", "marked": 0, "stop": 0}, {"id": 23, "word": "it", "marked": 0, "stop": 1}, {"id": 24, "word": "to", "marked": 0, "stop": 1}, {"id": 25, "word": "him", "marked": 0, "stop": 1}, {"id": 26, "word": ".", "marked": 0, "stop": 1}, {"id": 27, "word": "He", "marked": 0, "stop": 1}, {"id": 28, "word": "seized", "marked": 0, "stop": 0}, {"id": 29, "word": "it", "marked": 0, "stop": 1}, {"id": 30, "word": "firmly", "marked": 0, "stop": 0}, {"id": 31, "word": ",", "marked": 0, "stop": 1}, {"id": 32, "word": "and", "marked": 0, "stop": 1}, {"id": 33, "word": "pressed", "marked": 0, "stop": 0}, {"id": 34, "word": "it", "marked": 0, "stop": 1}, {"id": 35, "word": "so", "marked": 0, "stop": 1}, {"id": 36, "word": "hard", "marked": 0, "stop": 0}, {"id": 37, "word": "that", "marked": 0, "stop": 1}, {"id": 38, "word": "the", "marked": 0, "stop": 1}, {"id": 39, "word": "molten", "marked": 0, "stop": 1}, {"id": 40, "word": "iron", "marked": 0, "stop": 0}, {"id": 41, "word": "ran", "marked": 0, "stop": 0}, {"id": 42, "word": "down", "marked": 0, "stop": 1}, {"id": 43, "word": "between", "marked": 0, "stop": 1}, {"id": 44, "word": "his", "marked": 0, "stop": 1}, {"id": 45, "word": "fingers", "marked": 0, "stop": 0}, {"id": 46, "word": ".", "marked": 0, "stop": 1}]}, "3": {"title": "skalunda-giant", "s_id": 107, "id": 3, "words": [{"id": 0, "word": "``", "marked": 0, "stop": 1}, {"id": 1, "word": "Yes", "marked": 0, "stop": 0}, {"id": 2, "word": ",", "marked": 0, "stop": 1}, {"id": 3, "word": "there", "marked": 0, "stop": 1}, {"id": 4, "word": "is", "marked": 0, "stop": 1}, {"id": 5, "word": "still", "marked": 0, "stop": 1}, {"id": 6, "word": "warm", "marked": 0, "stop": 0}, {"id": 7, "word": "blood", "marked": 0, "stop": 0}, {"id": 8, "word": "to", "marked": 0, "stop": 1}, {"id": 9, "word": "be", "marked": 0, "stop": 1}, {"id": 10, "word": "found", "marked": 0, "stop": 0}, {"id": 11, "word": "in", "marked": 0, "stop": 1}, {"id": 12, "word": "Sweden", "marked": 0, "stop": 0}, {"id": 13, "word": ",", "marked": 0, "stop": 1}, {"id": 14, "word": "''", "marked": 0, "stop": 1}, {"id": 15, "word": "said", "marked": 0, "stop": 1}, {"id": 16, "word": "he", "marked": 0, "stop": 1}, {"id": 17, "word": ".", "marked": 0, "stop": 1}, {"id": 18, "word": "``", "marked": 0, "stop": 1}, {"id": 19, "word": "And", "marked": 0, "stop": 1}, {"id": 20, "word": "tell", "marked": 0, "stop": 0}, {"id": 21, "word": "me", "marked": 0, "stop": 1}, {"id": 22, "word": ",", "marked": 0, "stop": 1}, {"id": 23, "word": "''", "marked": 0, "stop": 1}, {"id": 24, "word": "he", "marked": 0, "stop": 1}, {"id": 25, "word": "continued", "marked": 0, "stop": 1}, {"id": 26, "word": ",", "marked": 0, "stop": 1}, {"id": 27, "word": "``", "marked": 0, "stop": 1}, {"id": 28, "word": "is", "marked": 0, "stop": 1}, {"id": 29, "word": "Skalunda", "marked": 0, "stop": 1}, {"id": 30, "word": "mountain", "marked": 0, "stop": 0}, {"id": 31, "word": "still", "marked": 0, "stop": 1}, {"id": 32, "word": "standing", "marked": 0, "stop": 0}, {"id": 33, "word": "?", "marked": 0, "stop": 1}, {"id": 34, "word": "''", "marked": 0, "stop": 1}, {"id": 35, "word": "``", "marked": 0, "stop": 1}, {"id": 36, "word": "No", "marked": 0, "stop": 1}, {"id": 37, "word": ",", "marked": 0, "stop": 1}, {"id": 38, "word": "the", "marked": 0, "stop": 1}, {"id": 39, "word": "hens", "marked": 0, "stop": 0}, {"id": 40, "word": "have", "marked": 0, "stop": 1}, {"id": 41, "word": "scratched", "marked": 0, "stop": 0}, {"id": 42, "word": "it", "marked": 0, "stop": 1}, {"id": 43, "word": "away", "marked": 0, "stop": 1}, {"id": 44, "word": ",", "marked": 0, "stop": 1}, {"id": 45, "word": "''", "marked": 0, "stop": 1}, {"id": 46, "word": "the", "marked": 0, "stop": 1}, {"id": 47, "word": "man", "marked": 0, "stop": 0}, {"id": 48, "word": "answered", "marked": 0, "stop": 0}, {"id": 49, "word": ".", "marked": 0, "stop": 1}, {"id": 50, "word": "``", "marked": 0, "stop": 1}, {"id": 51, "word": "How", "marked": 0, "stop": 1}, {"id": 52, "word": "could", "marked": 0, "stop": 1}, {"id": 53, "word": "it", "marked": 0, "stop": 1}, {"id": 54, "word": "last", "marked": 0, "stop": 1}, {"id": 55, "word": "?", "marked": 0, "stop": 1}, {"id": 56, "word": "''", "marked": 0, "stop": 1}, {"id": 57, "word": "said", "marked": 0, "stop": 1}, {"id": 58, "word": "the", "marked": 0, "stop": 1}, {"id": 59, "word": "giant", "marked": 0, "stop": 0}, {"id": 60, "word": ".", "marked": 0, "stop": 1}, {"id": 61, "word": "``", "marked": 0, "stop": 1}, {"id": 62, "word": "My", "marked": 0, "stop": 1}, {"id": 63, "word": "wife", "marked": 0, "stop": 0}, {"id": 64, "word": "and", "marked": 0, "stop": 1}, {"id": 65, "word": "daughter", "marked": 0, "stop": 0}, {"id": 66, "word": "piled", "marked": 0, "stop": 0}, {"id": 67, "word": "it", "marked": 0, "stop": 1}, {"id": 68, "word": "up", "marked": 0, "stop": 1}, {"id": 69, "word": "in", "marked": 0, "stop": 1}, {"id": 70, "word": "the", "marked": 0, "stop": 1}, {"id": 71, "word": "course", "marked": 0, "stop": 1}, {"id": 72, "word": "of", "marked": 0, "stop": 1}, {"id": 73, "word": "a", "marked": 0, "stop": 1}, {"id": 74, "word": "single", "marked": 0, "stop": 0}, {"id": 75, "word": "Sunday", "marked": 0, "stop": 0}, {"id": 76, "word": "morning", "marked": 0, "stop": 1}, {"id": 77, "word": ".", "marked": 0, "stop": 1}, {"id": 78, "word": "But", "marked": 0, "stop": 1}, {"id": 79, "word": "surely", "marked": 0, "stop": 1}, {"id": 80, "word": "the", "marked": 0, "stop": 1}, {"id": 81, "word": "Hallenberg", "marked": 0, "stop": 1}, {"id": 82, "word": "and", "marked": 0, "stop": 1}, {"id": 83, "word": "the", "marked": 0, "stop": 1}, {"id": 84, "word": "Hunneberg", "marked": 0, "stop": 1}, {"id": 85, "word": "are", "marked": 0, "stop": 1}, {"id": 86, "word": "still", "marked": 0, "stop": 1}, {"id": 87, "word": "standing", "marked": 0, "stop": 0}, {"id": 88, "word": ",", "marked": 0, "stop": 1}, {"id": 89, "word": "for", "marked": 0, "stop": 1}, {"id": 90, "word": "those", "marked": 0, "stop": 1}, {"id": 91, "word": "I", "marked": 0, "stop": 1}, {"id": 92, "word": "built", "marked": 0, "stop": 0}, {"id": 93, "word": "myself", "marked": 0, "stop": 1}, {"id": 94, "word": ".", "marked": 0, "stop": 1}, {"id": 95, "word": "''", "marked": 0, "stop": 1}]}, "4": {"title": "skalunda-giant", "s_id": 107, "id": 4, "words": [{"id": 0, "word": "When", "marked": 0, "stop": 1}, {"id": 1, "word": "the", "marked": 0, "stop": 1}, {"id": 2, "word": "man", "marked": 0, "stop": 0}, {"id": 3, "word": "had", "marked": 0, "stop": 1}, {"id": 4, "word": "confirmed", "marked": 0, "stop": 0}, {"id": 5, "word": "this", "marked": 0, "stop": 1}, {"id": 6, "word": ",", "marked": 0, "stop": 1}, {"id": 7, "word": "the", "marked": 0, "stop": 1}, {"id": 8, "word": "giant", "marked": 0, "stop": 0}, {"id": 9, "word": "wanted", "marked": 0, "stop": 0}, {"id": 10, "word": "to", "marked": 0, "stop": 1}, {"id": 11, "word": "know", "marked": 0, "stop": 0}, {"id": 12, "word": "whether", "marked": 0, "stop": 1}, {"id": 13, "word": "Karin", "marked": 0, "stop": 1}, {"id": 14, "word": "was", "marked": 0, "stop": 1}, {"id": 15, "word": "still", "marked": 0, "stop": 1}, {"id": 16, "word": "living", "marked": 0, "stop": 0}, {"id": 17, "word": "in", "marked": 0, "stop": 1}, {"id": 18, "word": "Stommen", "marked": 0, "stop": 1}, {"id": 19, "word": ".", "marked": 0, "stop": 1}, {"id": 20, "word": "And", "marked": 0, "stop": 1}, {"id": 21, "word": "when", "marked": 0, "stop": 1}, {"id": 22, "word": "they", "marked": 0, "stop": 1}, {"id": 23, "word": "told", "marked": 0, "stop": 1}, {"id": 24, "word": "him", "marked": 0, "stop": 1}, {"id": 25, "word": "that", "marked": 0, "stop": 1}, {"id": 26, "word": "she", "marked": 0, "stop": 1}, {"id": 27, "word": "was", "marked": 0, "stop": 1}, {"id": 28, "word": ",", "marked": 0, "stop": 1}, {"id": 29, "word": "he", "marked": 0, "stop": 1}, {"id": 30, "word": "gave", "marked": 0, "stop": 0}, {"id": 31, "word": "them", "marked": 0, "stop": 1}, {"id": 32, "word": "a", "marked": 0, "stop": 1}, {"id": 33, "word": "girdle", "marked": 0, "stop": 0}, {"id": 34, "word": ",", "marked": 0, "stop": 1}, {"id": 35, "word": "and", "marked": 0, "stop": 1}, {"id": 36, "word": "with", "marked": 0, "stop": 1}, {"id": 37, "word": "it", "marked": 0, "stop": 1}, {"id": 38, "word": "the", "marked": 0, "stop": 1}, {"id": 39, "word": "message", "marked": 0, "stop": 0}, {"id": 40, "word": "that", "marked": 0, "stop": 1}, {"id": 41, "word": "Karin", "marked": 0, "stop": 1}, {"id": 42, "word": "was", "marked": 0, "stop": 1}, {"id": 43, "word": "to", "marked": 0, "stop": 1}, {"id": 44, "word": "wear", "marked": 0, "stop": 0}, {"id": 45, "word": "it", "marked": 0, "stop": 1}, {"id": 46, "word": "in", "marked": 0, "stop": 1}, {"id": 47, "word": "remembrance", "marked": 0, "stop": 0}, {"id": 48, "word": "of", "marked": 0, "stop": 1}, {"id": 49, "word": "him", "marked": 0, "stop": 1}, {"id": 50, "word": ".", "marked": 0, "stop": 1}]}, "5": {"title": "skalunda-giant", "s_id": 107, "id": 5, "words": [{"id": 0, "word": "The", "marked": 0, "stop": 1}, {"id": 1, "word": "men", "marked": 0, "stop": 0}, {"id": 2, "word": "took", "marked": 0, "stop": 0}, {"id": 3, "word": "the", "marked": 0, "stop": 1}, {"id": 4, "word": "girdle", "marked": 0, "stop": 0}, {"id": 5, "word": "and", "marked": 0, "stop": 1}, {"id": 6, "word": "gave", "marked": 0, "stop": 0}, {"id": 7, "word": "it", "marked": 0, "stop": 1}, {"id": 8, "word": "to", "marked": 0, "stop": 1}, {"id": 9, "word": "Karin", "marked": 0, "stop": 1}, {"id": 10, "word": "upon", "marked": 0, "stop": 1}, {"id": 11, "word": "their", "marked": 0, "stop": 1}, {"id": 12, "word": "return", "marked": 0, "stop": 0}, {"id": 13, "word": "home", "marked": 0, "stop": 0}, {"id": 14, "word": ".", "marked": 0, "stop": 1}, {"id": 15, "word": "But", "marked": 0, "stop": 1}, {"id": 16, "word": "before", "marked": 0, "stop": 1}, {"id": 17, "word": "Karin", "marked": 0, "stop": 1}, {"id": 18, "word": "put", "marked": 0, "stop": 1}, {"id": 19, "word": "it", "marked": 0, "stop": 1}, {"id": 20, "word": "on", "marked": 0, "stop": 1}, {"id": 21, "word": ",", "marked": 0, "stop": 1}, {"id": 22, "word": "she", "marked": 0, "stop": 1}, {"id": 23, "word": "clasped", "marked": 0, "stop": 1}, {"id": 24, "word": "it", "marked": 0, "stop": 1}, {"id": 25, "word": "around", "marked": 0, "stop": 1}, {"id": 26, "word": "the", "marked": 0, "stop": 1}, {"id": 27, "word": "oak-tree", "marked": 0, "stop": 0}, {"id": 28, "word": "that", "marked": 0, "stop": 1}, {"id": 29, "word": "grew", "marked": 0, "stop": 0}, {"id": 30, "word": "in", "marked": 0, "stop": 1}, {"id": 31, "word": "the", "marked": 0, "stop": 1}, {"id": 32, "word": "court", "marked": 0, "stop": 1}, {"id": 33, "word": ".", "marked": 0, "stop": 1}, {"id": 34, "word": "No", "marked": 0, "stop": 1}, {"id": 35, "word": "sooner", "marked": 0, "stop": 1}, {"id": 36, "word": "had", "marked": 0, "stop": 1}, {"id": 37, "word": "she", "marked": 0, "stop": 1}, {"id": 38, "word": "done", "marked": 0, "stop": 1}, {"id": 39, "word": "so", "marked": 0, "stop": 1}, {"id": 40, "word": "than", "marked": 0, "stop": 1}, {"id": 41, "word": "the", "marked": 0, "stop": 1}, {"id": 42, "word": "oak", "marked": 0, "stop": 0}, {"id": 43, "word": "tore", "marked": 0, "stop": 0}, {"id": 44, "word": "itself", "marked": 0, "stop": 1}, {"id": 45, "word": "out", "marked": 0, "stop": 1}, {"id": 46, "word": "of", "marked": 0, "stop": 1}, {"id": 47, "word": "the", "marked": 0, "stop": 1}, {"id": 48, "word": "ground", "marked": 0, "stop": 0}, {"id": 49, "word": ",", "marked": 0, "stop": 1}, {"id": 50, "word": "and", "marked": 0, "stop": 1}, {"id": 51, "word": "flew", "marked": 0, "stop": 1}, {"id": 52, "word": "to", "marked": 0, "stop": 1}, {"id": 53, "word": "the", "marked": 0, "stop": 1}, {"id": 54, "word": "North", "marked": 0, "stop": 0}, {"id": 55, "word": ",", "marked": 0, "stop": 1}, {"id": 56, "word": "borne", "marked": 0, "stop": 1}, {"id": 57, "word": "away", "marked": 0, "stop": 1}, {"id": 58, "word": "by", "marked": 0, "stop": 1}, {"id": 59, "word": "the", "marked": 0, "stop": 1}, {"id": 60, "word": "storm-wind", "marked": 0, "stop": 1}, {"id": 61, "word": ".", "marked": 0, "stop": 1}, {"id": 62, "word": "In", "marked": 0, "stop": 1}, {"id": 63, "word": "the", "marked": 0, "stop": 1}, {"id": 64, "word": "place", "marked": 0, "stop": 0}, {"id": 65, "word": "where", "marked": 0, "stop": 1}, {"id": 66, "word": "it", "marked": 0, "stop": 1}, {"id": 67, "word": "had", "marked": 0, "stop": 1}, {"id": 68, "word": "stood", "marked": 0, "stop": 1}, {"id": 69, "word": "was", "marked": 0, "stop": 1}, {"id": 70, "word": "a", "marked": 0, "stop": 1}, {"id": 71, "word": "deep", "marked": 0, "stop": 0}, {"id": 72, "word": "pit", "marked": 0, "stop": 0}, {"id": 73, "word": ",", "marked": 0, "stop": 1}, {"id": 74, "word": "and", "marked": 0, "stop": 1}, {"id": 75, "word": "the", "marked": 0, "stop": 1}, {"id": 76, "word": "roots", "marked": 0, "stop": 0}, {"id": 77, "word": "of", "marked": 0, "stop": 1}, {"id": 78, "word": "the", "marked": 0, "stop": 1}, {"id": 79, "word": "tree", "marked": 0, "stop": 0}, {"id": 80, "word": "were", "marked": 0, "stop": 1}, {"id": 81, "word": "so", "marked": 0, "stop": 1}, {"id": 82, "word": "enormous", "marked": 0, "stop": 1}, {"id": 83, "word": "that", "marked": 0, "stop": 1}, {"id": 84, "word": "one", "marked": 0, "stop": 1}, {"id": 85, "word": "of", "marked": 0, "stop": 1}, {"id": 86, "word": "the", "marked": 0, "stop": 1}, {"id": 87, "word": "best", "marked": 0, "stop": 0}, {"id": 88, "word": "springs", "marked": 0, "stop": 0}, {"id": 89, "word": "in", "marked": 0, "stop": 1}, {"id": 90, "word": "Stommen", "marked": 0, "stop": 1}, {"id": 91, "word": "flows", "marked": 0, "stop": 0}, {"id": 92, "word": "from", "marked": 0, "stop": 1}, {"id": 93, "word": "one", "marked": 0, "stop": 1}, {"id": 94, "word": "of", "marked": 0, "stop": 1}, {"id": 95, "word": "the", "marked": 0, "stop": 1}, {"id": 96, "word": "root-holes", "marked": 0, "stop": 1}, {"id": 97, "word": "to", "marked": 0, "stop": 1}, {"id": 98, "word": "this", "marked": 0, "stop": 1}, {"id": 99, "word": "very", "marked": 0, "stop": 1}, {"id": 100, "word": "day", "marked": 0, "stop": 0}, {"id": 101, "word": ".", "marked": 0, "stop": 1}]}}